<?xml version="1.0" encoding="UTF-8"?>
<DOCUMENT><DESC></DESC><DESC></DESC><DESC></DESC><TIME>793</TIME><P><W> https://timesofindia.indiatimes.com/city/jammu/two-dead-three-injured-in-landslide-in-jammu-and-kashmirs-ramban/articleshow/68461696.cms </W></P><P><CASUALTIES-ARG ID="1"><LINK EVENT_ARG="0" ID="12" TYPE_REL="EVENT_ARG"/><W> Two </W><W> dead, </W><W> three </W><W> injured </W></CASUALTIES-ARG><W> in </W><NATURAL_EVENT ID="0" TYPE="LAND_SLIDE"><W> landslide </W></NATURAL_EVENT><W> in </W><PLACE-ARG ID="2"><LINK EVENT_ARG="0" ID="11" TYPE_REL="EVENT_ARG"/><W> Jammu </W><W> and </W><W> Kashmir&apos;s </W><W> Ramban </W></PLACE-ARG></P><P><W> BANIHAL: </W><CASUALTIES-ARG ID="3"><LINK EVENT_ARG="5" ID="15" TYPE_REL="EVENT_ARG"/><W> Two </W><W> persons </W><W> were </W><W> killed </W><W> and </W><W> three </W><W> others </W><W> injured </W></CASUALTIES-ARG><W> on </W><TIME-ARG ID="4"><LINK EVENT_ARG="5" ID="14" TYPE_REL="EVENT_ARG"/><W> Sunday </W></TIME-ARG><W> when </W><W> a </W><NATURAL_EVENT ID="5" TYPE="LAND_SLIDE"><EVENT-COREF-LINK EVENT_ID="0" ID="19" TYPE_REL="EVENT_COREF"/><W> landslide </W></NATURAL_EVENT><W> struck </W><W> a </W><W> remote </W><W> village </W><W> in </W><PLACE-ARG ID="6"><LINK EVENT_ARG="5" ID="13" TYPE_REL="EVENT_ARG"/><W> Jammu </W><W> and </W><W> Kashmir&apos;s </W><W> Ramban </W><W> district, </W></PLACE-ARG><W> police </W><W> said. </W></P><P><W> A </W><W> group </W><W> of </W><W> labourers </W><W> was </W><W> on </W><W> way </W><W> to </W><W> Banihal </W><W> on </W><W> foot </W><W> when </W><W> they </W><W> got </W><W> trapped </W><W> under </W><W> the </W><W> debris </W><W> after </W><W> the </W><NATURAL_EVENT ID="7" TYPE="LAND_SLIDE"><EVENT-COREF-LINK EVENT_ID="5" ID="20" TYPE_REL="EVENT_COREF"/><W> landslide </W></NATURAL_EVENT><W> occurred </W><W> at </W><PLACE-ARG ID="8"><LINK EVENT_ARG="7" ID="16" TYPE_REL="EVENT_ARG"/><W> Khari-Mahoo </W><W> road </W><W> near </W><W> Aarmarg </W></PLACE-ARG><W> in </W><W> the </W><TIME-ARG ID="9"><LINK EVENT_ARG="7" ID="17" TYPE_REL="EVENT_ARG"/><W> morning, </W></TIME-ARG><W> a </W><W> police </W><W> officer </W><W> said. </W></P><P><W> The </W><W> locals </W><W> pulled </W><W> out </W><W> the </W><W> body </W><W> of </W><W> Mohammad </W><W> Qasim </W><W> Gujjar </W><W> (33), </W><W> a </W><W> resident </W><W> of </W><W> Aarmarg, </W><W> from </W><W> underneath </W><W> the </W><W> rubble, </W><CASUALTIES-ARG ID="10"><LINK EVENT_ARG="7" ID="18" TYPE_REL="EVENT_ARG"/><W> while </W><W> four </W><W> others </W><W> injured </W></CASUALTIES-ARG><W> were </W><W> shifted </W><W> to </W><W> a </W><W> hospital. </W></P><P><W> Critically </W><W> injured </W><W> Abdulah </W><W> Gujjar </W><W> (61) </W><W> was </W><W> referred </W><W> to </W><W> a </W><W> hospital </W><W> in </W><W> Srinagar </W><W> but </W><W> succumbed </W><W> to </W><W> his </W><W> injuries, </W><W> the </W><W> officer </W><W> added. </W></P></DOCUMENT>