<?xml version="1.0" encoding="UTF-8"?>
<DOCUMENT><DESC></DESC><DESC></DESC><TIME>3715</TIME><P><W> https://www.thehindu.com/news/cities/Delhi/woman-driving-car-shot-at-in-delhi-condition-critical/article28367493.ece?homepage=true </W></P><P><W> Woman </W><W> driving </W><MAN_MADE_EVENT ID="14" TYPE="SHOOT_OUT"><W> car </W><W> shot </W></MAN_MADE_EVENT><W> at </W><W> in </W><PLACE-ARG ID="15"><LINK EVENT_ARG="14" ID="19" TYPE_REL="EVENT_ARG"/><W> Delhi, </W></PLACE-ARG><W> condition </W><W> critical </W></P><P><W> A </W><W> woman </W><W> was </W><MAN_MADE_EVENT ID="16" TYPE="SHOOT_OUT"><EVENT-COREF-LINK EVENT_ID="14" ID="26" TYPE_REL="EVENT_COREF"/><W> shot </W></MAN_MADE_EVENT><W> at </W><W> by </W><W> two </W><W> men </W><W> on </W><W> a </W><W> bike </W><W> while </W><W> she </W><W> was </W><W> driving </W><W> her </W><W> car </W><W> in </W><PLACE-ARG ID="2"><LINK EVENT_ARG="16" ID="20" TYPE_REL="EVENT_ARG"/><W> Dwarka </W><W> area </W></PLACE-ARG><W> on </W><TIME-ARG ID="3"><LINK EVENT_ARG="16" ID="21" TYPE_REL="EVENT_ARG"/><W> July </W><W> 11 </W><W> morning. </W></TIME-ARG></P><P><W> Police </W><W> said </W><W> a </W><W> PCR </W><W> call </W><W> was </W><W> received </W><W> at </W><W> 8 </W><W> a.m. </W><W> about </W><W> a </W><W> woman </W><W> being </W><MAN_MADE_EVENT ID="17" TYPE="SHOOT_OUT"><EVENT-COREF-LINK EVENT_ID="16" ID="27" TYPE_REL="EVENT_COREF"/><W> shot </W></MAN_MADE_EVENT><W> at </W><W> near </W><W> Radisson </W><W> Hotel </W><W> roundabout. </W><W> A </W><W> team </W><W> reached </W><W> the </W><W> spot </W><W> and </W><CASUALTIES-ARG ID="5"><LINK EVENT_ARG="17" ID="22" TYPE_REL="EVENT_ARG"/><W> the </W><W> injured </W><W> woman </W><W> was </W><W> rushed </W><W> to </W><W> a </W><W> hospital </W></CASUALTIES-ARG><W> where </W><W> she </W><W> is </W><W> undergoing </W><W> treatment. </W></P><P><W> An </W><W> eyewitness </W><W> said </W><W> that </W><W> after </W><W> being </W><MAN_MADE_EVENT ID="18" TYPE="SHOOT_OUT"><EVENT-COREF-LINK EVENT_ID="17" ID="28" TYPE_REL="EVENT_COREF"/><W> hit, </W></MAN_MADE_EVENT><W> the </W><REASON-ARG ID="8"><LINK EVENT_ARG="18" ID="23" TYPE_REL="EVENT_ARG"/><W> woman </W><W> lost </W><W> control </W><W> of </W><W> the </W><W> vehicle </W></REASON-ARG><W> and </W><MAN_MADE_EVENT ID="7" TYPE="ACCIDENTS"><W> rammed </W></MAN_MADE_EVENT><W> into </W><W> an </W><W> auto </W><W> rickshaw, </W><W> resulting </W><W> in </W><CASUALTIES-ARG ID="9"><LINK EVENT_ARG="18" ID="24" TYPE_REL="EVENT_ARG"/><W> minor </W><W> injuries </W><W> to </W><W> the </W><W> auto </W><W> driver. </W></CASUALTIES-ARG><W> The </W><W> car </W><W> came </W><W> to </W><W> a </W><W> halt </W><W> after </W><W> hitting </W><W> the </W><W> footpath. </W></P><P><W> “The </W><W> woman </W><W> has </W><W> been </W><W> identified </W><W> as </W><W> Kiran </W><W> Bala, </W><W> a </W><W> resident </W><W> of </W><W> Dwarka </W><W> Sector </W><W> 12. </W><W> She </W><W> was </W><W> driving </W><W> when </W><W> all </W><W> of </W><W> the </W><W> sudden </W><W> two </W><W> men </W><W> on </W><W> a </W><W> bike </W><MAN_MADE_EVENT ID="10" TYPE="SHOOT_OUT"><EVENT-COREF-LINK EVENT_ID="18" ID="30" TYPE_REL="EVENT_COREF"/><W> opened </W><W> fire </W></MAN_MADE_EVENT><W> on </W><W> her. </W><W> One </W><W> bullet </W><MAN_MADE_EVENT ID="11" TYPE="SHOOT_OUT"><EVENT-COREF-LINK EVENT_ID="10" ID="29" TYPE_REL="EVENT_COREF"/><W> hit </W></MAN_MADE_EVENT><W> her </W><W> in </W><W> the </W><W> hand </W><W> and </W><W> another </W><W> in </W><W> the </W><W> neck. </W><CASUALTIES-ARG ID="12"><LINK EVENT_ARG="11" ID="25" TYPE_REL="EVENT_ARG"/><W> Her </W><W> condition </W><W> is </W><W> critical,” </W></CASUALTIES-ARG><W> said </W><W> a </W><W> police </W><W> officer. </W></P><P><W> The </W><W> officer </W><W> added </W><W> that </W><W> the </W><W> family </W><W> members </W><W> have </W><W> been </W><W> informed </W><W> about </W><W> the </W><MAN_MADE_EVENT ID="13" TYPE="SHOOT_OUT"><EVENT-COREF-LINK EVENT_ID="11" ID="31" TYPE_REL="EVENT_COREF"/><W> incident. </W></MAN_MADE_EVENT></P><P><W> Police </W><W> teams </W><W> have </W><W> been </W><W> formed </W><W> to </W><W> identify </W><W> the </W><W> bikers. </W><W> Robbery </W><W> has </W><W> been </W><W> ruled </W><W> out </W><W> as </W><W> the </W><W> victim’s </W><W> mobile </W><W> phone </W><W> and </W><W> purse </W><W> were </W><W> in </W><W> the </W><W> car. </W></P></DOCUMENT>