<?xml version="1.0" encoding="UTF-8"?>
<DOCUMENT><DESC></DESC><DESC/><TIME>1392</TIME><P><W> https://www.hindustantimes.com/gurgaon/at-least-2-injured-as-truck-rams-several-vehicles-in-gurugram/story-zmK4WuQX6qHpgP7L72j4wL.html </W></P><P><CASUALTIES-ARG ID="1"><LINK EVENT_ARG="4" ID="26" TYPE_REL="EVENT_ARG"/><W> At </W><W> least </W><W> 2 </W><W> injured </W></CASUALTIES-ARG><W> as </W><MAN_MADE_EVENT ID="4" TYPE="VEHICULAR_COLLISION"><W> truck </W><W> rams </W></MAN_MADE_EVENT><W> several </W><W> vehicles </W><W> in </W><PLACE-ARG ID="2"><LINK EVENT_ARG="4" ID="25" TYPE_REL="EVENT_ARG"/><W> Gurugram </W></PLACE-ARG></P><P><W> gurgaon </W><W> Updated: </W><W> Jul </W><W> 16, </W><W> 2019 </W><W> 03:19 </W><W> IST </W></P><P><W> A </W><W> truck </W><W> trailer </W><W> of </W><W> a </W><W> private </W><W> company </W><W> allegedly </W><MAN_MADE_EVENT ID="3" TYPE="ACCIDENTS"><EVENT-COREF-LINK EVENT_ID="4" ID="41" TYPE_REL="EVENT_COREF"/><W> rammed </W></MAN_MADE_EVENT><W> into </W><W> at </W><W> least </W><W> three </W><W> vehicles </W><W> and </W><W> came </W><W> to </W><W> a </W><W> halt </W><W> after </W><MAN_MADE_EVENT ID="5" TYPE="VEHICULAR_COLLISION"><EVENT-COREF-LINK EVENT_ID="3" ID="42" TYPE_REL="EVENT_COREF"/><W> crashing </W></MAN_MADE_EVENT><W> into </W><W> a </W><W> tractor-trolley </W><W> at </W><PLACE-ARG ID="17"><LINK EVENT_ARG="5" ID="27" TYPE_REL="EVENT_ARG"/><W> Hipa </W><W> Chowk </W><W> in </W><W> Sector </W><W> 18 </W></PLACE-ARG><W> on </W><TIME-ARG ID="18"><LINK EVENT_ARG="5" ID="28" TYPE_REL="EVENT_ARG"/><W> Monday </W><W> afternoon. </W></TIME-ARG><W> One </W><W> of </W><W> the </W><CASUALTIES-ARG ID="19"><LINK EVENT_ARG="5" ID="29" TYPE_REL="EVENT_ARG"/><W> cars </W><W> overturned </W><W> upon </W><W> impact </W><W> while </W><W> others </W><W> were </W><W> severely </W><W> damaged. </W></CASUALTIES-ARG><W> The </W><W> police </W><W> said </W><W> no </W><W> casualties </W><W> were </W><W> reported </W><CASUALTIES-ARG ID="20"><LINK EVENT_ARG="5" ID="30" TYPE_REL="EVENT_ARG"/><W> but </W><W> at </W><W> least </W><W> two </W><W> persons </W><W> with </W><W> injuries </W></CASUALTIES-ARG><W> were </W><W> rushed </W><W> to </W><W> nearby </W><W> hospitals. </W></P><P><W> According </W><W> to </W><W> the </W><W> police, </W><W> the </W><MAN_MADE_EVENT ID="21" TYPE="VEHICULAR_COLLISION"><EVENT-COREF-LINK EVENT_ID="5" ID="43" TYPE_REL="EVENT_COREF"/><W> incident </W></MAN_MADE_EVENT><W> took </W><W> place </W><TIME-ARG ID="22"><LINK EVENT_ARG="21" ID="32" TYPE_REL="EVENT_ARG"/><W> around </W><W> 3pm </W></TIME-ARG><W> at </W><PLACE-ARG ID="23"><LINK EVENT_ARG="21" ID="31" TYPE_REL="EVENT_ARG"/><W> Hipa </W><W> Chowk, </W></PLACE-ARG><W> when </W><W> a </W><W> truck </W><W> trailer, </W><W> which </W><W> had </W><W> a </W><W> Rajasthan </W><W> registration </W><W> number </W><W> plate, </W><W> allegedly </W><W> jumped </W><W> a </W><W> red </W><W> light </W><W> and </W><MAN_MADE_EVENT ID="6" TYPE="VEHICULAR_COLLISION"><EVENT-COREF-LINK EVENT_ID="21" ID="45" TYPE_REL="EVENT_COREF"/><W> crashed </W></MAN_MADE_EVENT><W> into </W><W> an </W><W> SUV </W><W> (Bolero) </W><W> from </W><W> behind. </W><W> After </W><W> the </W><MAN_MADE_EVENT ID="7" TYPE="VEHICULAR_COLLISION"><EVENT-COREF-LINK EVENT_ID="6" ID="44" TYPE_REL="EVENT_COREF"/><W> collision, </W></MAN_MADE_EVENT><W> the </W><W> trailer </W><MAN_MADE_EVENT ID="8" TYPE="VEHICULAR_COLLISION"><EVENT-COREF-LINK EVENT_ID="7" ID="46" TYPE_REL="EVENT_COREF"/><W> hit </W></MAN_MADE_EVENT><W> an </W><CASUALTIES-ARG ID="36"><LINK EVENT_ARG="8" ID="37" TYPE_REL="EVENT_ARG"/><W> auto-rickshaw </W><W> from </W><W> the </W><W> side </W><W> and </W><W> grazed </W><W> a </W><W> Maruti </W><W> Eeco </W><W> van, </W><W> which </W><W> got </W><W> overturned </W><W> on </W><W> one </W><W> side </W><W> due </W><W> to </W><W> the </W><W> impact. </W></CASUALTIES-ARG></P><P><W> An </W><W> eyewitness, </W><W> requesting </W><W> anonymity, </W><W> said </W><W> the </W><W> trailer </W><W> veered </W><W> towards </W><W> a </W><W> tractor </W><W> trolley </W><W> and </W><W> came </W><W> to </W><W> a </W><W> halt </W><W> after </W><W> its </W><W> front </W><MAN_MADE_EVENT ID="9" TYPE="VEHICULAR_COLLISION"><EVENT-COREF-LINK EVENT_ID="8" ID="47" TYPE_REL="EVENT_COREF"/><W> hit </W></MAN_MADE_EVENT><W> the </W><W> tractor </W><W> from </W><W> the </W><W> right </W><W> side. </W><W> The </W><W> tractor </W><W> tyre </W><W> and </W><W> a </W><W> part </W><W> of </W><W> the </W><W> front </W><W> were </W><W> crushed </W><W> under </W><W> the </W><W> trailer. </W><W> “At </W><W> least </W><W> two </W><W> more </W><W> cars, </W><W> of </W><W> which </W><W> one </W><W> was </W><W> a </W><W> Brezza, </W><MAN_MADE_EVENT ID="38" TYPE="VEHICULAR_COLLISION"><EVENT-COREF-LINK EVENT_ID="9" ID="48" TYPE_REL="EVENT_COREF"/><W> crashed </W></MAN_MADE_EVENT><W> into </W><W> the </W><W> trolley </W><W> leading </W><W> to </W><W> a </W><W> pile-up. </W><W> The </W><MAN_MADE_EVENT ID="10" TYPE="VEHICULAR_COLLISION"><EVENT-COREF-LINK EVENT_ID="38" ID="49" TYPE_REL="EVENT_COREF"/><W> collision </W></MAN_MADE_EVENT><W> caused </W><W> traffic </W><W> congestion </W><W> in </W><W> the </W><W> stretch, </W><AFTER_EFFECTS-ARG ID="39"><LINK EVENT_ARG="10" ID="40" TYPE_REL="EVENT_ARG"/><W> which </W><W> was </W><W> cleared </W><W> after </W><W> an </W><W> hour </W></AFTER_EFFECTS-ARG><W> after </W><W> police </W><W> and </W><W> traffic </W><W> police </W><W> personnel </W><W> arrived,” </W><W> said </W><W> an </W><W> eyewitness. </W></P><P><W> Vivek </W><W> Kundu, </W><W> station </W><W> house </W><W> officer </W><W> (SHO), </W><W> Sector </W><W> 17/18 </W><W> police </W><W> station, </W><W> said </W><W> the </W><W> exact </W><W> sequence </W><W> of </W><W> events </W><W> is </W><W> not </W><W> known. </W><CASUALTIES-ARG ID="11"><LINK EVENT_ARG="10" ID="33" TYPE_REL="EVENT_ARG"/><W> “At </W><W> least </W><W> two </W><W> people </W><W> were </W><W> hospitalised </W><W> with </W><W> injuries. </W></CASUALTIES-ARG><W> We </W><W> are </W><W> trying </W><W> to </W><W> trace </W><W> the </W><W> trailer </W><W> driver, </W><W> who </W><W> is </W><W> absconding. </W></P><P><W> A </W><W> complaint </W><W> has </W><W> been </W><W> received </W><W> but </W><W> the </W><W> statements </W><W> of </W><W> the </W><W> victims </W><W> are </W><W> yet </W><W> to </W><W> be </W><W> recorded,” </W><W> said </W><W> SHO. </W></P><P><W> A </W><W> traffic </W><W> police </W><W> official, </W><W> requesting </W><W> anonymity, </W><W> said </W><W> that </W><W> the </W><MAN_MADE_EVENT ID="12" TYPE="VEHICULAR_COLLISION"><EVENT-COREF-LINK EVENT_ID="10" ID="50" TYPE_REL="EVENT_COREF"/><W> collision </W></MAN_MADE_EVENT><W> caused </W><W> a </W><W> traffic </W><W> snarl </W><W> at </W><W> the </W><W> stretch </W><W> lasting </W><W> up </W><W> to </W><W> a </W><W> kilometre </W><W> on </W><W> the </W><W> road </W><W> approaching </W><PLACE-ARG ID="24"><LINK EVENT_ARG="12" ID="34" TYPE_REL="EVENT_ARG"/><W> Old </W><W> Delhi-Gurgaon </W><W> Road. </W></PLACE-ARG></P><P><W> Vikas </W><W> Chopra, </W><W> who </W><W> works </W><W> as </W><W> the </W><W> IT </W><W> head </W><W> at </W><W> a </W><W> company </W><W> adjacent </W><W> to </W><W> the </W><W> spot </W><W> where </W><W> the </W><MAN_MADE_EVENT ID="13" TYPE="VEHICULAR_COLLISION"><EVENT-COREF-LINK EVENT_ID="12" ID="51" TYPE_REL="EVENT_COREF"/><W> collision </W></MAN_MADE_EVENT><W> took </W><W> place, </W><W> said </W><W> that </W><W> he </W><W> heard </W><W> the </W><W> sound </W><W> of </W><W> vehicles </W><MAN_MADE_EVENT ID="14" TYPE="VEHICULAR_COLLISION"><EVENT-COREF-LINK EVENT_ID="13" ID="52" TYPE_REL="EVENT_COREF"/><W> crashing </W></MAN_MADE_EVENT><W> and </W><W> rushed </W><W> outside. </W></P><P><W> “At </W><W> the </W><W> time, </W><W> the </W><W> trailer </W><W> driver </W><W> had </W><W> locked </W><W> himself </W><W> in </W><W> the </W><W> truck </W><W> and </W><W> was </W><W> refusing </W><W> to </W><W> come </W><W> out. </W><AFTER_EFFECTS-ARG ID="42"><LINK EVENT_ARG="15" ID="43" TYPE_REL="EVENT_ARG"/><W> His </W><W> colleague, </W><W> a </W><W> cleaner, </W><W> had </W><W> escaped </W><W> immediately </W></AFTER_EFFECTS-ARG><W> after </W><W> the </W><MAN_MADE_EVENT ID="15" TYPE="VEHICULAR_COLLISION"><EVENT-COREF-LINK EVENT_ID="14" ID="53" TYPE_REL="EVENT_COREF"/><W> incident. </W></MAN_MADE_EVENT><AFTER_EFFECTS-ARG ID="40"><LINK EVENT_ARG="15" ID="41" TYPE_REL="EVENT_ARG"/><W> The </W><W> traffic </W><W> was </W><W> cleared </W><W> up </W><W> after </W><W> at </W><W> least </W><W> 45 </W><W> minutes </W><W> and </W><W> a </W><W> crane </W><W> was </W><W> brought </W><W> to </W><W> remove </W><W> certain </W><W> vehicles,” </W><W> said </W><W> Chopra. </W></AFTER_EFFECTS-ARG></P><P><W> The </W><W> police </W><W> said </W><W> the </W><W> trailer </W><W> driver </W><W> had </W><W> escaped </W><W> by </W><W> the </W><W> time </W><W> they </W><W> reached </W><W> the </W><W> spot. </W></P></DOCUMENT>