<?xml version="1.0" encoding="UTF-8"?>
<DOCUMENT><DESC></DESC><DESC></DESC><DESC></DESC><DESC></DESC><DESC></DESC><TIME>2208</TIME><P><W> https://www.business-standard.com/article/pti-stories/theatre-stage-collapses-in-china-1-child-killed-14-injured-119052600205_1.html </W></P><P><W> Theatre </W><W> stage </W><MAN_MADE_EVENT ID="0" TYPE="MISCELLANEOUS"><W> collapses </W></MAN_MADE_EVENT><W> in </W><PLACE-ARG ID="1"><LINK EVENT_ARG="0" ID="10" TYPE_REL="EVENT_ARG"/><W> China; </W></PLACE-ARG><CASUALTIES-ARG ID="2"><LINK EVENT_ARG="0" ID="11" TYPE_REL="EVENT_ARG"/><W> 1 </W><W> child </W><W> killed, </W><W> 14 </W><W> injured </W></CASUALTIES-ARG></P><P><W> A </W><W> theatre </W><W> stage </W><MAN_MADE_EVENT ID="4" TYPE="MISCELLANEOUS"><EVENT-COREF-LINK EVENT_ID="0" ID="17" TYPE_REL="EVENT_COREF"/><W> collapsed </W></MAN_MADE_EVENT><W> during </W><W> a </W><W> dance </W><W> audition, </W><CASUALTIES-ARG ID="3"><LINK EVENT_ARG="4" ID="13" TYPE_REL="EVENT_ARG"/><W> killing </W><W> one </W><W> child </W><W> and </W><W> injuring </W><W> 14 </W><W> others </W></CASUALTIES-ARG><W> in </W><PLACE-ARG ID="5"><LINK EVENT_ARG="4" ID="12" TYPE_REL="EVENT_ARG"/><W> Zhangzhou </W><W> city </W><W> in </W><W> China&apos;s </W><W> Fujian </W><W> province. </W></PLACE-ARG></P><P><W> The </W><W> Jinshuixian </W><W> theatre </W><W> in </W><W> Zhangzhou </W><W> Development </W><W> Zone </W><W> hosted </W><W> a </W><W> children&apos;s </W><W> dance </W><W> audition </W><W> Saturday </W><W> night. </W></P><P><W> During </W><W> the </W><W> audition, </W><W> part </W><W> of </W><W> the </W><W> stage </W><MAN_MADE_EVENT ID="6" TYPE="MISCELLANEOUS"><EVENT-COREF-LINK EVENT_ID="4" ID="16" TYPE_REL="EVENT_COREF"/><W> collapsed </W></MAN_MADE_EVENT><W> in </W><W> which </W><W> a </W><CASUALTIES-ARG ID="7"><LINK EVENT_ARG="6" ID="15" TYPE_REL="EVENT_ARG"/><W> 13-year-old </W><W> participant </W><W> was </W><W> killed, </W></CASUALTIES-ARG><W> state-run </W><W> China </W><W> Daily </W><W> reported </W><W> on </W><TIME-ARG ID="8"><LINK EVENT_ARG="6" ID="14" TYPE_REL="EVENT_ARG"/><W> Sunday. </W></TIME-ARG></P><P><W> The </W><W> injured </W><W> participants </W><W> are </W><W> receiving </W><W> treatment </W><W> in </W><W> hospitals. </W><W> Companies </W><W> and </W><W> organisers </W><W> involved </W><W> in </W><W> the </W><MAN_MADE_EVENT ID="9" TYPE="MISCELLANEOUS"><W> accident </W></MAN_MADE_EVENT><W> are </W><W> in </W><W> police </W><W> custody, </W><W> the </W><W> report </W><W> said. </W></P></DOCUMENT>