<?xml version="1.0" encoding="UTF-8"?>
<DOCUMENT><DESC></DESC><DESC/><DESC/><TIME>2424</TIME><P><CASUALTIES-ARG ID="0"><LINK EVENT_ARG="1" ID="20" TYPE_REL="EVENT_ARG"/><W> 20 </W><W> children </W><W> among </W><W> 100 </W><W> killed </W></CASUALTIES-ARG><W> as </W><W> Syria </W><MAN_MADE_EVENT ID="1" TYPE="SURGICAL_STRIKES"><W> attacks </W><W> rebels </W></MAN_MADE_EVENT><W> in </W><PLACE-ARG ID="2"><LINK EVENT_ARG="1" ID="21" TYPE_REL="EVENT_ARG"/><W> Eastern </W><W> Ghouta </W></PLACE-ARG></P><P><W> Heavy </W><W> Syrian </W><W> bombardment </W><CASUALTIES-ARG ID="3"><LINK EVENT_ARG="31" ID="32" TYPE_REL="EVENT_ARG"/><W> killed </W><W> at </W><W> least </W><W> 100 </W><W> civilians </W></CASUALTIES-ARG><W> in </W><MAN_MADE_EVENT ID="31" TYPE="SURGICAL_STRIKES"><W> rebel-held </W></MAN_MADE_EVENT><PLACE-ARG ID="4"><LINK EVENT_ARG="31" ID="33" TYPE_REL="EVENT_ARG"/><W> eastern </W><W> Ghouta </W></PLACE-ARG><W> on </W><TIME-ARG ID="5"><LINK EVENT_ARG="31" ID="34" TYPE_REL="EVENT_ARG"/><W> Monday, </W></TIME-ARG><W> a </W><W> war </W><W> monitor </W><W> said, </W><W> as </W><W> regime </W><W> forces </W><W> appeared </W><W> to </W><W> prepare </W><W> for </W><W> an </W><W> imminent </W><W> ground </W><W> assault. </W></P><P><W> The </W><W> escalation </W><W> came </W><W> as </W><W> pro-government </W><W> forces </W><W> were </W><W> also </W><W> expected </W><W> to </W><W> enter </W><W> the </W><W> northern </W><W> Kurdish-controlled </W><W> enclave </W><W> of </W><W> Afrin, </W><W> to </W><W> take </W><W> a </W><W> stand </W><W> against </W><W> a </W><W> month-old </W><W> Turkish </W><W> assault </W><W> there. </W></P><P><W> Held </W><W> by </W><W> rebels </W><W> since </W><W> 2012, </W><W> Eastern </W><W> Ghouta </W><W> is </W><W> the </W><W> last </W><W> opposition </W><W> pocket </W><W> around </W><W> Damascus </W><W> and </W><W> President </W><W> Bashar </W><W> al-Assad </W><W> has </W><W> dispatched </W><W> reinforcements </W><W> there </W><W> in </W><W> an </W><W> apparent </W><W> concerted </W><W> effort </W><W> to </W><W> retake </W><W> it. </W></P><P><W> A </W><W> barrage </W><W> of </W><MAN_MADE_EVENT ID="6" TYPE="SURGICAL_STRIKES"><W> air </W><W> strikes, </W></MAN_MADE_EVENT><W> rocket </W><W> fire </W><W> and </W><W> artillery </W><W> slammed </W><W> into </W><W> several </W><W> towns </W><W> across </W><PLACE-ARG ID="7"><LINK EVENT_ARG="6" ID="22" TYPE_REL="EVENT_ARG"/><W> Eastern </W><W> Ghouta </W></PLACE-ARG><W> on </W><TIME-ARG ID="8"><LINK EVENT_ARG="6" ID="23" TYPE_REL="EVENT_ARG"/><W> Monday. </W></TIME-ARG></P><P><W> The </W><W> Britain-based </W><W> Syrian </W><W> Observatory </W><W> for </W><W> Human </W><W> Rights </W><W> said </W><W> at </W><W> least </W><CASUALTIES-ARG ID="9"><LINK EVENT_ARG="6" ID="24" TYPE_REL="EVENT_ARG"/><W> 20 </W><W> children </W><W> were </W><W> among </W><W> 100 </W><W> civilians </W><W> killed </W><W> in </W><W> the </W><W> assault, </W><W> while </W><W> around </W><W> 300 </W><W> other </W><W> people </W><W> were </W><W> wounded. </W></CASUALTIES-ARG></P><P><W> “The </W><W> regime </W><W> is </W><W> bombing </W><W> Eastern </W><W> Ghouta </W><W> to </W><W> pave </W><W> the </W><W> way </W><W> for </W><W> a </W><W> ground </W><W> offensive,” </W><W> said </W><W> Observatory </W><W> head </W><W> Rami </W><W> Abdel </W><W> Rahman. </W></P><P><W> The </W><W> main </W><W> opposition </W><W> National </W><W> Coalition, </W><W> which </W><W> is </W><W> based </W><W> in </W><W> Turkey, </W><W> denounced </W><W> the </W><W> “war </W><W> of </W><W> extermination” </W><W> in </W><W> Eastern </W><W> Ghouta </W><W> as </W><W> well </W><W> as </W><W> the </W><W> “international </W><W> silence”. </W></P><P><W> In </W><W> a </W><W> statement, </W><W> it </W><W> also </W><W> accused </W><W> regime </W><W> ally </W><W> Russia </W><W> of </W><W> seeking </W><W> to </W><W> “bury </W><W> the </W><W> political </W><W> process” </W><W> for </W><W> a </W><W> solution </W><W> to </W><W> the </W><W> conflict. </W></P><P><W> Residents </W><W> of </W><W> Hammuriyeh </W><W> could </W><W> be </W><W> seen </W><W> rushing </W><W> indoors </W><W> in </W><W> panic </W><W> as </W><W> soon </W><W> as </W><W> they </W><W> heard </W><W> the </W><W> sound </W><W> of </W><W> airplanes. </W></P><P><W> Alaa </W><W> al-Din, </W><W> a </W><W> 23-year-old </W><W> Syrian </W><W> in </W><W> Hammuriyeh, </W><W> said </W><W> civilians </W><W> were </W><W> afraid </W><W> of </W><W> a </W><W> potential </W><W> government </W><W> offensive. </W></P><P><W> “Ghouta’s </W><W> fate </W><W> is </W><W> unknown. </W><W> We’ve </W><W> got </W><W> nothing </W><W> but </W><W> God’s </W><W> mercy </W><W> and </W><W> hiding </W><W> out </W><W> in </W><W> our </W><W> basements,” </W><W> he </W><W> told </W><W> AFP. </W><W> “There’s </W><W> no </W><W> alternative.” </W></P><P><W> Wailing </W><W> children </W></P><P><W> Shelling </W><W> also </W><W> hit </W><W> the </W><W> town </W><W> of </W><W> Douma, </W><W> where </W><W> an </W><W> AFP </W><W> correspondent </W><W> saw </W><W> five </W><W> toddlers </W><W> brought </W><W> to </W><W> a </W><W> hospital, </W><W> covered </W><W> in </W><W> dust </W><W> and </W><W> wailing </W><W> uncontrollably. </W></P><P><W> The </W><W> hospital </W><W> was </W><W> full </W><W> of </W><W> distraught </W><W> civilians: </W><W> one </W><W> father </W><W> slapped </W><W> his </W><W> forehead </W><W> after </W><W> finding </W><W> his </W><W> two </W><W> dead </W><W> children, </W><W> another </W><W> erupted </W><W> into </W><W> tears </W><W> as </W><W> he </W><W> discovered </W><W> the </W><W> body </W><W> of </W><W> his </W><W> newborn </W><W> on </W><W> a </W><W> purple </W><W> sheet </W><W> next </W><W> to </W><W> a </W><W> pool </W><W> of </W><W> blood. </W></P><P><W> Eastern </W><W> Ghouta </W><W> is </W><W> held </W><W> by </W><W> two </W><W> main </W><W> Islamist </W><W> factions, </W><W> while </W><W> jihadists </W><W> control </W><W> small </W><W> pockets </W><W> including </W><W> one </W><W> directly </W><W> adjacent </W><W> to </W><W> the </W><W> capital. </W></P><P><W> The </W><W> Observatory </W><W> and </W><W> Syrian </W><W> daily </W><W> newspaper </W><W> Al-Watan </W><W> had </W><W> said </W><W> negotiations </W><W> were </W><W> under </W><W> way </W><W> for </W><W> the </W><W> evacuation </W><W> of </W><W> jihadists </W><W> from </W><W> Eastern </W><W> Ghouta. </W></P><P><W> But </W><W> escalating </W><W> military </W><W> pressure </W><W> indicate </W><W> that </W><W> the </W><W> regime </W><W> would </W><W> opt </W><W> for </W><W> a </W><W> ground </W><W> assault </W><W> instead </W><W> of </W><W> talks, </W><W> the </W><W> monitor </W><W> said. </W></P><P><W> Government </W><W> troops </W><W> carried </W><W> out </W><W> a </W><W> relentless </W><W> five-day </W><W> bombing </W><W> campaign </W><W> earlier </W><W> this </W><W> month </W><W> that </W><W> killed </W><W> around </W><W> 250 </W><W> civilians </W><W> in </W><W> the </W><W> enclave </W><W> and </W><W> wounded </W><W> hundreds. </W></P><P><W> Around </W><W> the </W><W> same </W><W> time, </W><W> the </W><W> monitor </W><W> said, </W><W> the </W><W> regime </W><W> began </W><W> dispatching </W><W> military </W><W> reinforcements </W><W> to </W><W> Eastern </W><W> Ghouta. </W></P><P><W> After </W><W> days </W><W> of </W><W> relative </W><W> calm, </W><W> the </W><W> government </W><W> sent </W><W> more </W><W> than </W><W> 260 </W><W> rockets </W><W> sailing </W><W> onto </W><W> Eastern </W><W> Ghouta </W><W> on </W><W> Sunday. </W></P><P><W> Those </W><W> rockets, </W><W> as </W><W> well </W><W> as </W><W> artillery </W><W> fire </W><W> and </W><MAN_MADE_EVENT ID="10" TYPE="SURGICAL_STRIKES"><W> air </W><W> strikes, </W></MAN_MADE_EVENT><CASUALTIES-ARG ID="11"><LINK EVENT_ARG="10" ID="25" TYPE_REL="EVENT_ARG"/><W> killed </W><W> 17 </W><W> civilians, </W></CASUALTIES-ARG><W> said </W><W> the </W><W> Observatory. </W></P><P><W> The </W><W> regime </W><W> is </W><W> keen </W><W> to </W><W> regain </W><W> control </W><W> of </W><W> Eastern </W><W> Ghouta </W><W> to </W><W> halt </W><W> the </W><W> deadly </W><W> salvo </W><W> of </W><W> rockets </W><W> and </W><W> mortars </W><W> that </W><W> rebels </W><W> fire </W><W> on </W><W> Damascus. </W></P><P><W> About </W><W> half </W><W> a </W><W> dozen </W><W> rockets </W><W> hit </W><W> the </W><W> capital </W><W> Sunday </W><W> night, </W><W> AFP </W><W> correspondents </W><W> said. </W><W> State </W><W> news </W><W> agency </W><W> SANA </W><W> reported </W><W> that </W><W> one </W><W> person </W><W> was </W><W> killed. </W></P><P><W> More </W><W> than </W><CASUALTIES-ARG ID="12"><LINK EVENT_ARG="13" ID="26" TYPE_REL="EVENT_ARG"/><W> 20 </W><W> civilians </W><W> have </W><W> been </W><W> killed </W></CASUALTIES-ARG><W> by </W><MAN_MADE_EVENT ID="13" TYPE="SURGICAL_STRIKES"><W> rebel </W><W> fire </W></MAN_MADE_EVENT><TIME-ARG ID="14"><LINK EVENT_ARG="13" ID="27" TYPE_REL="EVENT_ARG"/><W> this </W><W> month </W></TIME-ARG><W> alone </W><W> in </W><W> regime-held </W><PLACE-ARG ID="15"><LINK EVENT_ARG="13" ID="28" TYPE_REL="EVENT_ARG"/><W> Damascus. </W></PLACE-ARG></P><P><W> Regime </W><W> to </W><W> enter </W><W> Afrin? </W></P><P><W> All </W><W> was </W><W> quiet </W><W> in </W><W> the </W><W> capital </W><W> on </W><W> Monday </W><W> but </W><W> since </W><W> rumours </W><W> of </W><W> an </W><W> imminent </W><W> assault </W><W> on </W><W> Eastern </W><W> Ghouta </W><W> started </W><W> spreading, </W><W> people </W><W> living </W><W> close </W><W> to </W><W> the </W><W> rebel </W><W> enclave </W><W> started </W><W> packing </W><W> their </W><W> bags. </W></P><P><W> Jawad </W><W> al-Obros, </W><W> 30, </W><W> said </W><W> he </W><W> was </W><W> looking </W><W> to </W><W> move </W><W> to </W><W> a </W><W> hotel </W><W> in </W><W> the </W><W> western </W><W> sector </W><W> of </W><W> the </W><W> city </W><W> to </W><W> escape </W><W> his </W><W> home </W><W> in </W><W> an </W><W> east </W><W> Damascus </W><W> neighbourhood </W><W> that </W><W> has </W><W> been </W><W> regularly </W><W> hit </W><W> by </W><W> rockets </W><W> from </W><W> Ghouta. </W></P><P><W> “We’re </W><W> tired </W><W> of </W><W> this </W><W> situation. </W><W> It </W><W> seems </W><W> that </W><W> there’s </W><W> no </W><W> solution </W><W> but </W><W> a </W><W> full-blown </W><W> military </W><W> one,” </W><W> he </W><W> told </W><W> AFP. </W></P><P><CASUALTIES-ARG ID="17"><LINK EVENT_ARG="18" ID="29" TYPE_REL="EVENT_ARG"/><W> More </W><W> than </W><W> 340,000 </W><W> people </W><W> have </W><W> been </W><W> killed </W></CASUALTIES-ARG><W> since </W><W> Syria’s </W><MAN_MADE_EVENT ID="18" TYPE="SURGICAL_STRIKES"><W> conflict </W></MAN_MADE_EVENT><W> erupted </W><W> in </W><TIME-ARG ID="19"><LINK EVENT_ARG="18" ID="30" TYPE_REL="EVENT_ARG"/><W> 2011 </W></TIME-ARG><W> with </W><W> protests </W><W> against </W><W> Assad’s </W><W> government. </W></P><P><W> It </W><W> has </W><W> since </W><W> evolved </W><W> into </W><W> a </W><W> war </W><W> that </W><W> has </W><W> carved </W><W> up </W><W> the </W><W> country </W><W> into </W><W> rival </W><W> zones </W><W> of </W><W> influence </W><W> among </W><W> the </W><W> regime, </W><W> rebels, </W><W> jihadists </W><W> and </W><W> Kurdish </W><W> forces. </W></P><P><W> The </W><W> Kurdish </W><W> People’s </W><W> Protection </W><W> Units </W><W> (YPG) </W><W> control </W><W> the </W><W> northwestern </W><W> region </W><W> of </W><W> Afrin, </W><W> target </W><W> of </W><W> a </W><W> month-old </W><W> assault </W><W> by </W><W> the </W><W> Turkish </W><W> army </W><W> and </W><W> allied </W><W> Syrian </W><W> rebels. </W></P><P><W> Turkey </W><W> sees </W><W> the </W><W> YPG </W><W> as </W><W> a </W><W> “terror” </W><W> group </W><W> linked </W><W> to </W><W> the </W><W> Kurdistan </W><W> Workers </W><W> Party </W><W> (PKK), </W><W> outlawed </W><W> by </W><W> Ankara, </W><W> and </W><W> wants </W><W> to </W><W> clear </W><W> it </W><W> from </W><W> its </W><W> southern </W><W> border. </W></P><P><W> The </W><W> YPG </W><W> has </W><W> controlled </W><W> Afrin </W><W> since </W><W> 2012, </W><W> when </W><W> Syrian </W><W> troops </W><W> withdrew </W><W> from </W><W> it </W><W> and </W><W> other </W><W> Kurdish-majority </W><W> areas. </W></P><P><W> Syrian </W><W> state </W><W> media </W><W> said </W><W> Monday </W><W> that </W><W> pro-regime </W><W> forces </W><W> were </W><W> preparing </W><W> to </W><W> enter </W><W> the </W><W> area </W><W> to </W><W> “join </W><W> the </W><W> resistance </W><W> against </W><W> the </W><W> Turkish </W><W> aggression”. </W></P><P><W> Turkey </W><W> warned </W><W> against </W><W> any </W><W> bid </W><W> by </W><W> the </W><W> Syrian </W><W> regime </W><W> to </W><W> help </W><W> the </W><W> YPG. </W></P><P><W> President </W><W> Recep </W><W> Tayyip </W><W> Erdogan </W><W> spoke </W><W> on </W><W> the </W><W> phone </W><W> with </W><W> Russian </W><W> counterpart </W><W> Vladimir </W><W> Putin </W><W> and, </W><W> according </W><W> to </W><W> Turkish </W><W> media, </W><W> told </W><W> him </W><W> any </W><W> support </W><W> from </W><W> Damascus </W><W> to </W><W> the </W><W> YPG </W><W> in </W><W> Afrin </W><W> “will </W><W> have </W><W> consequences” </W><W> for </W><W> the </W><W> regime. </W></P></DOCUMENT>