<?xml version="1.0" encoding="UTF-8"?>
<DOCUMENT><DESC></DESC><DESC/><DESC/><TIME>488</TIME><P><W> https://timesofindia.indiatimes.com/city/agra/up-four-kanwarias-killed-two-injured-in-road-accident/articleshow/70511968.cms </W></P><P><W> UP: </W><CASUALTIES-ARG ID="2"><LINK EVENT_ARG="0" ID="14" TYPE_REL="EVENT_ARG"/><W> Four </W><W> kanwarias </W><W> killed, </W><W> two </W><W> injured </W></CASUALTIES-ARG><W> in </W><MAN_MADE_EVENT ID="0" TYPE="ACCIDENTS"><W> road </W><W> accident </W></MAN_MADE_EVENT><W> in </W><PLACE-ARG ID="1"><LINK EVENT_ARG="0" ID="13" TYPE_REL="EVENT_ARG"/><W> Agra </W></PLACE-ARG></P><P><W> Arvind </W><W> Chauhan </W><W> | </W><W> TNN </W><W> | </W><W> Updated: </W><W> Aug </W><W> 3, </W><W> 2019, </W><W> 17:10 </W><W> IST </W></P><P><W> AGRA: </W><CASUALTIES-ARG ID="3"><LINK EVENT_ARG="5" ID="16" TYPE_REL="EVENT_ARG"/><W> Four </W><W> kanwarias </W><W> were </W><W> killed </W><W> and </W><W> two </W><W> others </W><W> were </W><W> injured </W></CASUALTIES-ARG><W> in </W><PLACE-ARG ID="4"><LINK EVENT_ARG="5" ID="15" TYPE_REL="EVENT_ARG"/><W> Uttar </W><W> Pradesh&apos;s </W><W> Agra </W><W> district </W></PLACE-ARG><W> after </W><W> a </W><W> truck </W><MAN_MADE_EVENT ID="5" TYPE="ACCIDENTS"><EVENT-COREF-LINK EVENT_ID="0" ID="23" TYPE_REL="EVENT_COREF"/><W> hit </W></MAN_MADE_EVENT><W> the </W><W> rear </W><W> of </W><W> a </W><W> tractor-trolley </W><W> in </W><W> which </W><W> the </W><W> victims </W><W> were </W><W> traveling. </W></P><P><W> The </W><MAN_MADE_EVENT ID="6" TYPE="ACCIDENTS"><EVENT-COREF-LINK EVENT_ID="5" ID="24" TYPE_REL="EVENT_COREF"/><W> accident </W></MAN_MADE_EVENT><W> took </W><W> place </W><W> in </W><TIME-ARG ID="18"><LINK EVENT_ARG="6" ID="19" TYPE_REL="EVENT_ARG"/><W> the </W><W> intervening </W><W> night </W><W> of </W><W> Friday </W><W> and </W><W> Saturday </W></TIME-ARG><W> on </W><PLACE-ARG ID="7"><LINK EVENT_ARG="6" ID="17" TYPE_REL="EVENT_ARG"/><W> Agra-Mumbai </W><W> Highway </W></PLACE-ARG><W> near </W><W> Jonai </W><W> mod </W><W> of </W><W> Saiyan </W><W> police </W><W> jurisdiction. </W></P><P><CASUALTIES-ARG ID="8"><LINK EVENT_ARG="6" ID="20" TYPE_REL="EVENT_ARG"/><W> The </W><W> deceased </W><W> were </W><W> identified </W><W> as </W><W> Omprakash, </W><W> Rajesh, </W><W> Yogesh </W><W> and </W><W> Ram </W><W> Hari </W></CASUALTIES-ARG><W> who </W><W> hailed </W><W> from </W><W> Iradatnagar </W><W> police </W><W> jurisdiction. </W></P><P><W> Speaking </W><W> to </W><W> TOI, </W><W> Baijnath </W><W> Singh, </W><W> station </W><W> house </W><W> officer </W><W> of </W><W> Saiyan, </W><W> said, </W><W> “A </W><W> group </W><W> of </W><W> nearly </W><W> 15-20 </W><W> kanwarias </W><W> was </W><W> travelling </W><W> in </W><W> a </W><W> tractor-trolley </W><REASON-ARG ID="9"><LINK EVENT_ARG="11" ID="21" TYPE_REL="EVENT_ARG"/><W> when </W><W> suddenly </W><W> a </W><W> cattle </W><W> appeared </W><W> on </W><W> the </W><W> road </W><W> following </W><W> which </W><W> the </W><W> driver </W><W> applied </W><W> sudden </W><W> brake. </W></REASON-ARG><W> But </W><W> unfortunately, </W><REASON-ARG ID="10"><LINK EVENT_ARG="11" ID="22" TYPE_REL="EVENT_ARG"/><W> a </W><W> truck </W><W> cruising </W><W> behind </W><W> the </W><W> tractor </W><W> failed </W><W> to </W><W> control </W><W> its </W><W> speed </W></REASON-ARG><W> and </W><MAN_MADE_EVENT ID="11" TYPE="ACCIDENTS"><EVENT-COREF-LINK EVENT_ID="6" ID="25" TYPE_REL="EVENT_COREF"/><W> hit </W></MAN_MADE_EVENT><W> the </W><W> rear </W><W> of </W><W> tractor-trolley.” </W></P><P><W> “After </W><W> the </W><MAN_MADE_EVENT ID="12" TYPE="ACCIDENTS"><EVENT-COREF-LINK EVENT_ID="11" ID="26" TYPE_REL="EVENT_COREF"/><W> accident, </W></MAN_MADE_EVENT><W> the </W><W> truck </W><W> driver </W><W> fled </W><W> away. </W><AFTER_EFFECTS-ARG ID="19"><LINK EVENT_ARG="12" ID="20" TYPE_REL="EVENT_ARG"/><W> The </W><W> injured </W><W> have </W><W> been </W><W> admitted </W><W> in </W><W> hospital, </W><W> while </W><W> the </W><W> deceased </W><W> victims&apos; </W><W> bodies </W><W> have </W><W> been </W><W> sent </W><W> for </W><W> autopsy,” </W></AFTER_EFFECTS-ARG><W> said </W><W> SHO. </W></P><P><W> He </W><W> added, </W><W> “Based </W><W> on </W><W> victim’s </W><W> relative </W><W> written </W><W> complaint, </W><W> an </W><W> FIR </W><W> of </W><W> rash, </W><W> negligent </W><W> driving </W><W> causing </W><W> death </W><W> has </W><W> been </W><W> lodged </W><W> against </W><W> unknown </W><W> truck </W><W> driver.” </W></P></DOCUMENT>